FloodMaster/__init__.py
FloodMaster/forecasters/LstmPredictor.py
FloodMaster/forecasters/__init__.py
FloodMaster/forecasters/predictor.py
FloodMaster/routes/LstmPredictorApi.py
FloodMaster/routes/__init__.py
FloodMaster/schedulers/__init__.py
FloodMaster/schedulers/agent.py
FloodMaster/schedulers/controller.py
FloodMaster/schedulers/env.py
FloodMaster/schedulers/processor.py
FloodMaster/schedulers/space.py
FloodMaster/utils/CategoryEncoder.py
FloodMaster/utils/DataAnalyzer.py
FloodMaster/utils/DataFilters.py
FloodMaster/utils/DataLoader.py
FloodMaster/utils/DataPreprocessor.py
FloodMaster/utils/DataScaler.py
FloodMaster/utils/__init__.py
GRFloodMaster-1.1.0.dist-info/METADATA
GRFloodMaster-1.1.0.dist-info/WHEEL
GRFloodMaster-1.1.0.dist-info/top_level.txt
GRFloodMaster-1.1.0.dist-info/RECORD
