Metadata-Version: 2.1
Name: GRFloodMaster
Version: 1.1.0
Summary: 贵仁-智能雨洪管理模型
Home-page: https://cloud.keepsoft.net/product
License: UNKNOWN
Platform: UNKNOWN
Classifier: Programming Language :: Python :: 3.9
